pyrympro/__init__.py
pyrympro/const.py
pyrympro/rympro.py
pyrympro-0.0.8.dist-info/LICENSE
pyrympro-0.0.8.dist-info/METADATA
pyrympro-0.0.8.dist-info/WHEEL
pyrympro-0.0.8.dist-info/top_level.txt
pyrympro-0.0.8.dist-info/RECORD
