Metadata-Version: 2.1
Name: pyrympro
Version: 0.0.8
Summary: A python library to communitcate with Read Your Meter Pro (https://rym-pro.com/).
Home-page: https://github.com/OnFreund/pyrympro
Author: On Freund
Author-email: onfreund@gmail.com
License: MIT
Classifier: License :: OSI Approved :: MIT License
Classifier: Programming Language :: Python
Classifier: Programming Language :: Python :: 3
Classifier: Programming Language :: Python :: 3.7
Classifier: Programming Language :: Python :: Implementation :: CPython
Classifier: Programming Language :: Python :: Implementation :: PyPy
Requires-Python: >=3.10.0
License-File: LICENSE
Requires-Dist: aiohttp
